flattering/__init__.py
flattering/__version__.py
flattering/cli.py
tests/__init__.py
tests/test_csv.py
flattering-0.1.0.dist-info/AUTHORS
flattering-0.1.0.dist-info/LICENSE
flattering-0.1.0.dist-info/METADATA
flattering-0.1.0.dist-info/WHEEL
flattering-0.1.0.dist-info/entry_points.txt
flattering-0.1.0.dist-info/top_level.txt
flattering-0.1.0.dist-info/RECORD
