Metadata-Version: 2.1
Name: flattering
Version: 0.1.0
Summary: UNKNOWN
Home-page: UNKNOWN
Author: UNKNOWN
Author-email: UNKNOWN
License: UNKNOWN
Platform: UNKNOWN
Requires-Dist: attrs (>=21.2.0)
Requires-Dist: scalpl (>=0.4.2)
